dronefly/discord/__init__.py
dronefly/discord/embeds.py
dronefly/discord/menus.py
dronefly_discord-0.1.5.dist-info/LICENSE
dronefly_discord-0.1.5.dist-info/METADATA
dronefly_discord-0.1.5.dist-info/WHEEL
dronefly_discord-0.1.5.dist-info/RECORD
