Metadata-Version: 2.1
Name: dronefly-discord
Version: 0.1.5
Summary: Dronefly Discord library
License: AGPL-3.0-or-later
Author: Ben Armstrong
Author-email: synrg@debian.org
Requires-Python: >=3.11,<3.12
Classifier: License :: OSI Approved :: GNU Affero General Public License v3 or later (AGPLv3+)
Classifier: Programming Language :: Python :: 3
Classifier: Programming Language :: Python :: 3.11
Requires-Dist: discord-py (>=2.3.1)
Requires-Dist: dronefly-core (==0.3.9)
Requires-Dist: inflect (>=5.3.0,<6.0.0)
Requires-Dist: pyinaturalist (>=0.20.0,<0.21.0)
